LICENSE
README.rst
setup.py
BLACKFORGE003/BLACKFORGE.py
BLACKFORGE003/__init__.py
BLACKFORGE003.egg-info/PKG-INFO
BLACKFORGE003.egg-info/SOURCES.txt
BLACKFORGE003.egg-info/dependency_links.txt
BLACKFORGE003.egg-info/requires.txt
BLACKFORGE003.egg-info/top_level.txt